ipymarkup/__init__.py
ipymarkup/demo.py
ipymarkup/dep.py
ipymarkup/palette.py
ipymarkup/record.py
ipymarkup/show.py
ipymarkup/span.py
ipymarkup-0.9.0.dist-info/LICENSE
ipymarkup-0.9.0.dist-info/METADATA
ipymarkup-0.9.0.dist-info/WHEEL
ipymarkup-0.9.0.dist-info/top_level.txt
ipymarkup-0.9.0.dist-info/RECORD
