Metadata-Version: 2.1
Name: ipymarkup
Version: 0.9.0
Summary: NER, syntax tree markup visualisations for Jupyter Notebook
Home-page: https://github.com/natasha/ipymarkup
Author: Alexander Kukushkin
Author-email: alex@alexkuk.ru
License: MIT
Keywords: ner,syntax tree,markup,jupyter,ipython
Platform: UNKNOWN
Classifier: License :: OSI Approved :: MIT License
Classifier: Programming Language :: Python :: 3
Classifier: Topic :: Scientific/Engineering :: Artificial Intelligence
Classifier: Topic :: Scientific/Engineering :: Visualization
